langevals_legacy/lib/setup_legacy_packages.py
langevals_legacy/ragas_answer_correctness.py
langevals_legacy/ragas_answer_relevancy.py
langevals_legacy/ragas_context_precision.py
langevals_legacy/ragas_context_recall.py
langevals_legacy/ragas_context_relevancy.py
langevals_legacy/ragas_context_utilization.py
langevals_legacy/ragas_faithfulness.py
langevals_legacy/ragas_lib/common.py
langevals_legacy/ragas_lib/model_to_langchain.py
langevals_legacy/vendor/legacy_ragas/__init__.py
langevals_legacy/vendor/legacy_ragas/_analytics.py
langevals_legacy/vendor/legacy_ragas/_version.py
langevals_legacy/vendor/legacy_ragas/adaptation.py
langevals_legacy/vendor/legacy_ragas/async_utils.py
langevals_legacy/vendor/legacy_ragas/callbacks.py
langevals_legacy/vendor/legacy_ragas/embeddings/__init__.py
langevals_legacy/vendor/legacy_ragas/embeddings/base.py
langevals_legacy/vendor/legacy_ragas/evaluation.py
langevals_legacy/vendor/legacy_ragas/exceptions.py
langevals_legacy/vendor/legacy_ragas/executor.py
langevals_legacy/vendor/legacy_ragas/integrations/__init__.py
langevals_legacy/vendor/legacy_ragas/integrations/langchain.py
langevals_legacy/vendor/legacy_ragas/integrations/langsmith.py
langevals_legacy/vendor/legacy_ragas/llms/__init__.py
langevals_legacy/vendor/legacy_ragas/llms/base.py
langevals_legacy/vendor/legacy_ragas/llms/json_load.py
langevals_legacy/vendor/legacy_ragas/llms/output_parser.py
langevals_legacy/vendor/legacy_ragas/llms/prompt.py
langevals_legacy/vendor/legacy_ragas/metrics/__init__.py
langevals_legacy/vendor/legacy_ragas/metrics/_answer_correctness.py
langevals_legacy/vendor/legacy_ragas/metrics/_answer_relevance.py
langevals_legacy/vendor/legacy_ragas/metrics/_answer_similarity.py
langevals_legacy/vendor/legacy_ragas/metrics/_context_entities_recall.py
langevals_legacy/vendor/legacy_ragas/metrics/_context_precision.py
langevals_legacy/vendor/legacy_ragas/metrics/_context_recall.py
langevals_legacy/vendor/legacy_ragas/metrics/_context_relevancy.py
langevals_legacy-0.1.14.dist-info/METADATA
langevals_legacy-0.1.14.dist-info/WHEEL
langevals_legacy-0.1.14.dist-info/RECORD
