Metadata-Version: 2.4
Name: langevals-legacy
Version: 0.1.14
Summary: LangEvals Legacy evaluator
License: MIT
Author: Rogerio Chaves
Author-email: rogerio@langwatch.ai
Requires-Python: >=3.11,<4.0
Classifier: License :: OSI Approved :: MIT License
Classifier: Programming Language :: Python :: 3
Classifier: Programming Language :: Python :: 3.11
Classifier: Programming Language :: Python :: 3.12
Classifier: Programming Language :: Python :: 3.13
Classifier: Programming Language :: Python :: 3.14
Requires-Dist: appdirs (>=1.4.4,<2.0.0)
Requires-Dist: datasets (==2.14.6)
Requires-Dist: langchain-openai (>=0.1.23)
Requires-Dist: langchain_community (>=0.2.16)
Requires-Dist: langevals-core (>=0.1.18,<0.2.0)
Requires-Dist: litellm (==1.76.0)
Requires-Dist: pysbd (>=0.3.4,<0.4.0)
